bin/so-hk-tool
so3g-0.2.5.dist-info/RECORD
so3g-0.2.5.dist-info/WHEEL
so3g-0.2.5.dist-info/top_level.txt
so3g-0.2.5.dist-info/METADATA
so3g-0.2.5.dist-info/licenses/LICENSE
so3g-0.2.5.data/scripts/spt3g-inspect
so3g-0.2.5.data/scripts/gen-analysis-doc
so3g-0.2.5.data/scripts/spt3g-dump
so3g-0.2.5.data/scripts/spt3g-arc-dump
so3g-0.2.5.data/scripts/spt3g-verify
so3g-0.2.5.data/scripts/ledgerman.py
so3g-0.2.5.data/scripts/spt3g-arc-verify
so3g-0.2.5.data/scripts/spt3g-coadd-maps
so3g/spt3g.py
so3g/load_pybindings.py
so3g/g3reader_shim.py
so3g/__init__.py
so3g/libso3g.dylib
so3g/proj/coords.py
so3g/proj/util.py
so3g/proj/weather.py
so3g/proj/__init__.py
so3g/proj/quat.py
so3g/proj/ranges.py
so3g/proj/wcs.py
so3g/proj/mapthreads.py
so3g/hk/tree.py
so3g/hk/scanner.py
so3g/hk/util.py
so3g/hk/session.py
so3g/hk/__init__.py
so3g/hk/getdata.py
so3g/hk/cli.py
so3g/hk/translator.py
so3g/spt3g_internal/libspt3g-core.dylib
so3g/spt3g_internal/version.py
so3g/spt3g_internal/libspt3g-dfmux.dylib
so3g/spt3g_internal/__init__.py
so3g/spt3g_internal/dload.so
so3g/spt3g_internal/libspt3g-gcp.dylib
so3g/spt3g_internal/libspt3g-maps.dylib
so3g/spt3g_internal/libspt3g-calibration.dylib
so3g/spt3g_internal/maps/map_modules.py
so3g/spt3g_internal/maps/fitsio.py
so3g/spt3g_internal/maps/__init__.py
so3g/spt3g_internal/maps/skymapaddons.py
so3g/spt3g_internal/maps/coordsysmodules.py
so3g/spt3g_internal/maps/finals2000A.all
so3g/spt3g_internal/maps/maputils.py
so3g/spt3g_internal/maps/quathelpers.py
so3g/spt3g_internal/maps/azel.py
so3g/spt3g_internal/core/frameextensions.py
so3g/spt3g_internal/core/g3decorators.py
so3g/spt3g_internal/core/util.py
so3g/spt3g_internal/core/load_pybindings.py
so3g/spt3g_internal/core/modconstruct.py
so3g/spt3g_internal/core/__init__.py
so3g/spt3g_internal/core/timestreamextensions.py
so3g/spt3g_internal/core/g3logging.py
so3g/spt3g_internal/core/dataextensions.py
so3g/spt3g_internal/core/multiprocess.py
so3g/spt3g_internal/core/funcconstruct.py
so3g/spt3g_internal/core/docparser.py
so3g/spt3g_internal/core/fileio.py
