Metadata-Version: 2.4
Name: so3g
Version: 0.2.5
Summary: Tools for Simons Observatory work with spt3g_software
License: MIT License
Project-URL: source, https://github.com/simonsobs/so3g
Classifier: Development Status :: 5 - Production/Stable
Classifier: Environment :: Console
Classifier: Intended Audience :: Science/Research
Classifier: License :: OSI Approved :: BSD License
Classifier: Topic :: Scientific/Engineering :: Astronomy
Classifier: Programming Language :: Python :: 3.10
Classifier: Programming Language :: Python :: 3.11
Classifier: Programming Language :: Python :: 3.12
Classifier: Programming Language :: Python :: 3.13
Requires-Python: >=3.10
License-File: LICENSE
Requires-Dist: numpy
Requires-Dist: scipy
Requires-Dist: astropy
Requires-Dist: matplotlib
Requires-Dist: ephem
Requires-Dist: pytz
Requires-Dist: pyaml
Requires-Dist: sqlalchemy
Requires-Dist: tqdm
Requires-Dist: qpoint
Dynamic: license-file
